generate/__init__.py
generate/generate.py
generate/generate_config.py
generate_config/__init__.py
generate_config/generate.py
generate_config/generate_config.py
sog_devops_client-1.0.2.dist-info/LICENSE
sog_devops_client-1.0.2.dist-info/METADATA
sog_devops_client-1.0.2.dist-info/WHEEL
sog_devops_client-1.0.2.dist-info/top_level.txt
sog_devops_client-1.0.2.dist-info/RECORD
